django_email_token_auth-0.2.1.dist-info/DESCRIPTION.rst
django_email_token_auth-0.2.1.dist-info/METADATA
django_email_token_auth-0.2.1.dist-info/RECORD
django_email_token_auth-0.2.1.dist-info/WHEEL
django_email_token_auth-0.2.1.dist-info/metadata.json
django_email_token_auth-0.2.1.dist-info/top_level.txt
emailuser/__init__.py
emailuser/admin.py
emailuser/auth.py
emailuser/models.py
emailuser/urls.py
emailuser/views.py
emailuser/templates/user/auth.html
emailuser/templates/user/login.html
