Metadata-Version: 2.0
Name: django-email-token-auth
Version: 0.2.1
Summary: Simple email-token auth django app
Home-page: https://bitbucket.org/pi11/django-email-auth
Author: UNKNOWN
Author-email: UNKNOWN
License: UNKNOWN
Platform: UNKNOWN
